LICENSE
MANIFEST.in
README
chiki_jssdk.py
setup.py
chiki_jssdk.egg-info/PKG-INFO
chiki_jssdk.egg-info/SOURCES.txt
chiki_jssdk.egg-info/dependency_links.txt
chiki_jssdk.egg-info/not-zip-safe
chiki_jssdk.egg-info/requires.txt
chiki_jssdk.egg-info/top_level.txt