Metadata-Version: 1.0
Name: chiki-jssdk
Version: 0.0.1
Summary: chiki jssdk libs.
Home-page: https://github.com/endsh/chiki-jssdk
Author: Linshao
Author-email: 438985635@qq.com
License: UNKNOWN
Platform: any
